modelsettings
