Metadata-Version: 1.0
Name: modelsettings
Version: 1.6.4
Summary: Model your application settings.
Home-page: http://github.com/cidrblock/modelsettings
Author: Bradley A. Thornton
Author-email: brad@thethorntons.net
License: MIT
Platform: UNKNOWN
